LICENSE
MANIFEST.in
README.md
requirements.txt
setup.cfg
setup.py
himama/__init__.py
himama/__main__.py
himama.egg-info/PKG-INFO
himama.egg-info/SOURCES.txt
himama.egg-info/dependency_links.txt
himama.egg-info/entry_points.txt
himama.egg-info/requires.txt
himama.egg-info/top_level.txt
himama.egg-info/zip-safe