Metadata-Version: 2.1
Name: himama
Version: 0.0.4
Summary: himama: HiMama Downloader
Home-page: http://github.com/guilt/himama
Author: Karthik Kumar Viswanathan
Author-email: karthikkumar@gmail.com
License: MIT
Keywords: himama playschool daycare offline backup scrape
Platform: UNKNOWN
Classifier: Topic :: Software Development :: Libraries
Classifier: Programming Language :: Python :: 3.9
Classifier: Programming Language :: Python :: 3.10
Classifier: Programming Language :: Python :: 3.11
License-File: LICENSE
